letta/__init__.py
letta/agent.py
letta/agents/__init__.py
letta/agents/base_agent.py
letta/agents/ephemeral_agent.py
letta/agents/ephemeral_summary_agent.py
letta/agents/exceptions.py
letta/agents/helpers.py
letta/agents/letta_agent.py
letta/agents/letta_agent_batch.py
letta/agents/voice_agent.py
letta/agents/voice_sleeptime_agent.py
letta/cli/cli.py
letta/cli/cli_load.py
letta/client/__init__.py
letta/client/streaming.py
letta/client/utils.py
letta/config.py
letta/constants.py
letta/data_sources/__init__.py
letta/data_sources/connectors.py
letta/data_sources/connectors_helper.py
letta/data_sources/redis_client.py
letta/embeddings.py
letta/errors.py
letta/functions/__init__.py
letta/functions/ast_parsers.py
letta/functions/async_composio_toolset.py
letta/functions/composio_helpers.py
letta/functions/function_sets/base.py
letta/functions/function_sets/builtin.py
letta/functions/function_sets/extras.py
letta/functions/function_sets/files.py
letta/functions/function_sets/multi_agent.py
letta/functions/function_sets/voice.py
letta/functions/functions.py
letta/functions/helpers.py
letta/functions/interface.py
letta/functions/mcp_client/exceptions.py
letta/functions/mcp_client/types.py
letta/functions/prompts.py
letta/functions/schema_generator.py
letta/functions/schema_validator.py
letta/functions/types.py
letta/functions/typescript_parser.py
letta/groups/dynamic_multi_agent.py
letta/groups/helpers.py
letta/groups/round_robin_multi_agent.py
letta/groups/sleeptime_multi_agent.py
letta/groups/sleeptime_multi_agent_v2.py
letta/groups/supervisor_multi_agent.py
letta/helpers/__init__.py
letta/helpers/composio_helpers.py
letta/helpers/converters.py
letta/helpers/datetime_helpers.py
letta/helpers/decorators.py
letta/helpers/json_helpers.py
letta/helpers/message_helper.py
letta/helpers/pinecone_utils.py
letta/helpers/reasoning_helper.py
letta/helpers/singleton.py
letta/helpers/tool_execution_helper.py
letta/helpers/tool_rule_solver.py
letta/humans/__init__.py
letta_nightly-0.11.5.dist-info/LICENSE
letta_nightly-0.11.5.dist-info/METADATA
letta_nightly-0.11.5.dist-info/WHEEL
letta_nightly-0.11.5.dist-info/entry_points.txt
letta_nightly-0.11.5.dist-info/RECORD
