Metadata-Version: 2.1
Name: letta-nightly
Version: 0.11.5
Summary: Create LLM agents with long-term memory and custom tools
License: Apache License
Author: Letta Team
Author-email: contact@letta.com
Requires-Python: >=3.11,<3.14
Classifier: License :: Other/Proprietary License
Classifier: Programming Language :: Python :: 3
Classifier: Programming Language :: Python :: 3.11
Classifier: Programming Language :: Python :: 3.12
Provides-Extra: all
Provides-Extra: bedrock
Provides-Extra: cloud-tool-sandbox
Provides-Extra: desktop
Provides-Extra: dev
Provides-Extra: experimental
Provides-Extra: external-tools
Provides-Extra: google
Provides-Extra: pinecone
Provides-Extra: postgres
Provides-Extra: redis
Provides-Extra: server
Provides-Extra: tests
Requires-Dist: aioboto3 (>=14.3.0,<15.0.0) ; extra == "bedrock"
Requires-Dist: aiomultiprocess (>=0.9.1,<0.10.0)
Requires-Dist: alembic (>=1.13.3,<2.0.0)
Requires-Dist: anthropic (>=0.49.0,<0.50.0)
Requires-Dist: apscheduler (>=3.11.0,<4.0.0)
Requires-Dist: asyncpg (>=0.30.0,<0.31.0) ; extra == "postgres"
Requires-Dist: autoflake (>=2.3.0,<3.0.0) ; extra == "dev" or extra == "all"
Requires-Dist: black[jupyter] (>=24.2.0,<25.0.0) ; extra == "dev" or extra == "all"
Requires-Dist: boto3 (>=1.36.24,<2.0.0) ; extra == "bedrock"
Requires-Dist: brotli (>=1.1.0,<2.0.0)
Requires-Dist: certifi (>=2025.6.15,<2026.0.0)
Requires-Dist: colorama (>=0.4.6,<0.5.0)
Requires-Dist: composio-core (>=0.7.7,<0.8.0)
Requires-Dist: datamodel-code-generator[http] (>=0.25.0,<0.26.0)
Requires-Dist: demjson3 (>=3.0.6,<4.0.0)
Requires-Dist: docker (>=7.1.0,<8.0.0) ; extra == "external-tools" or extra == "desktop" or extra == "all"
Requires-Dist: docstring-parser (>=0.16,<0.17)
Requires-Dist: e2b-code-interpreter (>=1.0.3,<2.0.0) ; extra == "cloud-tool-sandbox"
Requires-Dist: faker (>=36.1.0,<37.0.0)
Requires-Dist: fastapi (>=0.115.6,<0.116.0) ; extra == "server" or extra == "desktop" or extra == "all"
Requires-Dist: firecrawl-py (>=2.8.0,<3.0.0) ; extra == "external-tools"
Requires-Dist: google-cloud-profiler (>=4.1.0,<5.0.0) ; extra == "experimental" or extra == "all"
Requires-Dist: google-genai (>=1.15.0,<2.0.0) ; extra == "google"
Requires-Dist: granian[reload] (>=2.3.2,<3.0.0) ; extra == "experimental" or extra == "all"
Requires-Dist: grpcio (>=1.68.1,<2.0.0)
Requires-Dist: grpcio-tools (>=1.68.1,<2.0.0)
Requires-Dist: html2text (>=2020.1.16,<2021.0.0)
Requires-Dist: httpx (>=0.28.0,<0.29.0)
Requires-Dist: httpx-sse (>=0.4.0,<0.5.0)
Requires-Dist: isort (>=5.13.2,<6.0.0) ; extra == "dev" or extra == "all"
Requires-Dist: jinja2 (>=3.1.5,<4.0.0)
Requires-Dist: langchain (>=0.3.7,<0.4.0) ; extra == "external-tools" or extra == "desktop" or extra == "all"
Requires-Dist: langchain-community (>=0.3.7,<0.4.0) ; extra == "external-tools" or extra == "desktop" or extra == "all"
Requires-Dist: letta_client (>=0.1.277,<0.2.0)
Requires-Dist: llama-index (>=0.12.2,<0.13.0)
Requires-Dist: llama-index-embeddings-openai (>=0.3.1,<0.4.0)
Requires-Dist: locust (>=2.31.5,<3.0.0) ; extra == "dev" or extra == "desktop" or extra == "all"
Requires-Dist: markitdown[docx,pdf,pptx] (>=0.1.2,<0.2.0)
Requires-Dist: marshmallow-sqlalchemy (>=1.4.1,<2.0.0)
Requires-Dist: matplotlib (>=3.10.1,<4.0.0)
Requires-Dist: mcp[cli] (>=1.9.4,<2.0.0)
Requires-Dist: mistralai (>=1.8.1,<2.0.0)
Requires-Dist: modal (>=1.1.0,<2.0.0) ; extra == "cloud-tool-sandbox"
Requires-Dist: nltk (>=3.8.1,<4.0.0)
Requires-Dist: numpy (>=2.1.0,<3.0.0)
Requires-Dist: openai (>=1.99.9,<2.0.0)
Requires-Dist: opentelemetry-api (==1.30.0)
Requires-Dist: opentelemetry-exporter-otlp (==1.30.0)
Requires-Dist: opentelemetry-instrumentation-requests (==0.51b0)
Requires-Dist: opentelemetry-instrumentation-sqlalchemy (==0.51b0)
Requires-Dist: opentelemetry-sdk (==1.30.0)
Requires-Dist: orjson (>=3.11.1,<4.0.0)
Requires-Dist: pathvalidate (>=3.2.1,<4.0.0)
Requires-Dist: pexpect (>=4.9.0,<5.0.0) ; extra == "dev" or extra == "all"
Requires-Dist: pg8000 (>=1.30.3,<2.0.0) ; extra == "postgres" or extra == "all"
Requires-Dist: pgvector (>=0.2.3,<0.3.0) ; extra == "postgres" or extra == "desktop" or extra == "all"
Requires-Dist: pinecone[asyncio] (>=7.3.0,<8.0.0) ; extra == "pinecone" or extra == "all"
Requires-Dist: pre-commit (>=3.5.0,<4.0.0) ; extra == "dev" or extra == "all"
Requires-Dist: prettytable (>=3.9.0,<4.0.0)
Requires-Dist: psycopg2 (>=2.9.10,<3.0.0) ; extra == "postgres" or extra == "all"
Requires-Dist: psycopg2-binary (>=2.9.10,<3.0.0) ; extra == "postgres" or extra == "all"
Requires-Dist: pydantic (>=2.10.6,<3.0.0)
Requires-Dist: pydantic-settings (>=2.2.1,<3.0.0)
Requires-Dist: pyhumps (>=3.8.0,<4.0.0)
Requires-Dist: pyright (>=1.1.347,<2.0.0) ; extra == "dev" or extra == "desktop" or extra == "all"
Requires-Dist: pytest-asyncio (>=0.24.0,<0.25.0) ; extra == "dev" or extra == "all"
Requires-Dist: pytest-order (>=1.2.0,<2.0.0) ; extra == "dev" or extra == "all"
Requires-Dist: python-box (>=7.1.1,<8.0.0)
Requires-Dist: python-multipart (>=0.0.19,<0.0.20)
Requires-Dist: pytz (>=2023.3.post1,<2024.0)
Requires-Dist: pyyaml (>=6.0.1,<7.0.0)
Requires-Dist: questionary (>=2.0.1,<3.0.0)
Requires-Dist: redis (>=6.2.0,<7.0.0) ; extra == "redis" or extra == "all"
Requires-Dist: rich (>=13.9.4,<14.0.0)
Requires-Dist: sentry-sdk[fastapi] (==2.19.1)
Requires-Dist: setuptools (>=70,<71)
Requires-Dist: sqlalchemy-json (>=0.7.0,<0.8.0)
Requires-Dist: sqlalchemy-utils (>=0.41.2,<0.42.0)
Requires-Dist: sqlalchemy[asyncio] (>=2.0.41,<3.0.0)
Requires-Dist: sqlite-vec (>=0.1.7a2,<0.2.0) ; extra == "desktop"
Requires-Dist: sqlmodel (>=0.0.16,<0.0.17)
Requires-Dist: structlog (>=25.4.0,<26.0.0)
Requires-Dist: tavily-python (>=0.7.2,<0.8.0)
Requires-Dist: tqdm (>=4.66.1,<5.0.0)
Requires-Dist: turbopuffer (>=0.5.17,<0.6.0) ; extra == "all"
Requires-Dist: typer (>=0.15.2,<0.16.0)
Requires-Dist: uvicorn (>=0.24.0.post1,<0.25.0) ; extra == "server" or extra == "desktop" or extra == "all"
Requires-Dist: uvloop (>=0.21.0,<0.22.0) ; (sys_platform != "win32") and (extra == "experimental" or extra == "all")
Requires-Dist: wikipedia (>=1.4.0,<2.0.0) ; extra == "external-tools" or extra == "tests" or extra == "desktop" or extra == "all"
